gpx_parser/GPX.py
gpx_parser/GPXTrack.py
gpx_parser/GPXTrackPoint.py
gpx_parser/GPXTrackSegment.py
gpx_parser/__init__.py
gpx_parser/parser.py
gpx_parser/utils.py
gpx_parser/xml_loader.py
gpx_parser-0.0.4.dist-info/METADATA
gpx_parser-0.0.4.dist-info/RECORD
gpx_parser-0.0.4.dist-info/WHEEL
gpx_parser-0.0.4.dist-info/top_level.txt
