Metadata-Version: 1.1
Name: gpx-parser
Version: 0.0.4
Summary: Simple parser for gpx tracks, segments, and points with latitude, longitude, and time.
Home-page: https://github.com/kholkolg/gpx_parser
Author: Olga Kholkovskaia
Author-email: olga.kholkovskaia@gmail.com
License: MIT
Download-URL: https://github.com/kholkolg/gpx_parser/
Platform: UNKNOWN
Classifier: Programming Language :: Python :: 3.4
Classifier: License :: OSI Approved :: MIT License
Classifier: Operating System :: OS Independent
